{
  "crawl_time": "2026-04-29T09:42:30.948868",
  "total_posts": 60,
  "posts": [
    {
      "title": "90년대 퇴폐업소 단속 레전드",
      "url": "https://www.bobaedream.co.kr/view?code=best&No=984284&vdate=",
      "site": "bobae",
      "category": "인기",
      "author": "콩Gspo..",
      "views": 18752,
      "likes": 113,
      "comments": 37,
      "popularity_score": 19089,
      "crawled_time": "2026-04-29T09:42:24.481621"
    },
    {
      "title": "어느 여자의 남자한테 철벽친 후...후기",
      "url": "https://www.bobaedream.co.kr/view?code=best&No=984292&vdate=",
      "site": "bobae",
      "category": "인기",
      "author": "wonde..",
      "views": 17728,
      "likes": 167,
      "comments": 34,
      "popularity_score": 18164,
      "crawled_time": "2026-04-29T09:42:24.481630"
    },
    {
      "title": "헬스갤 멸치인증남",
      "url": "https://www.bobaedream.co.kr/view?code=best&No=984291&vdate=",
      "site": "bobae",
      "category": "인기",
      "author": "화끈한청바..",
      "views": 17051,
      "likes": 106,
      "comments": 30,
      "popularity_score": 17353,
      "crawled_time": "2026-04-29T09:42:24.481631"
    },
    {
      "title": "모델 사진처럼 잘라 달라고 했는데  ㅠㅠ",
      "url": "https://www.bobaedream.co.kr/view?code=best&No=984293&vdate=",
      "site": "bobae",
      "category": "인기",
      "author": "일차로는추..",
      "views": 14723,
      "likes": 91,
      "comments": 41,
      "popularity_score": 15028,
      "crawled_time": "2026-04-29T09:42:24.481632"
    },
    {
      "title": "잘생긴게 최고라는 걸 보여줬던 프로그램",
      "url": "https://www.bobaedream.co.kr/view?code=best&No=984287&vdate=",
      "site": "bobae",
      "category": "인기",
      "author": "일차로는추..",
      "views": 13252,
      "likes": 63,
      "comments": 24,
      "popularity_score": 13450,
      "crawled_time": "2026-04-29T09:42:24.481633"
    },
    {
      "title": "길가다 택시기사 폭행범을 목격한 상남자 반응",
      "url": "https://www.bobaedream.co.kr/view?code=best&No=984283&vdate=",
      "site": "bobae",
      "category": "인기",
      "author": "사패산꼴데",
      "views": 12004,
      "likes": 125,
      "comments": 10,
      "popularity_score": 12284,
      "crawled_time": "2026-04-29T09:42:24.481634"
    },
    {
      "title": "의외로 금속노조에 소속되어 있는 회사",
      "url": "https://www.bobaedream.co.kr/view?code=best&No=984298&vdate=",
      "site": "bobae",
      "category": "인기",
      "author": "화끈한청바..",
      "views": 10723,
      "likes": 103,
      "comments": 17,
      "popularity_score": 10980,
      "crawled_time": "2026-04-29T09:42:24.481635"
    },
    {
      "title": "고양이를 잃어버린 태국인",
      "url": "https://www.bobaedream.co.kr/view?code=best&No=984285&vdate=",
      "site": "bobae",
      "category": "인기",
      "author": "star0..",
      "views": 10587,
      "likes": 115,
      "comments": 11,
      "popularity_score": 10850,
      "crawled_time": "2026-04-29T09:42:24.481640"
    },
    {
      "title": "중국 경제 역대급 심각한 상황 ㄷㄷ",
      "url": "https://www.bobaedream.co.kr/view?code=best&No=984309&vdate=",
      "site": "bobae",
      "category": "인기",
      "author": "썩열이나라",
      "views": 9638,
      "likes": 86,
      "comments": 26,
      "popularity_score": 9888,
      "crawled_time": "2026-04-29T09:42:24.481641"
    },
    {
      "title": "약관 동의하면 여자로 살아야 함",
      "url": "https://www.bobaedream.co.kr/view?code=best&No=984297&vdate=",
      "site": "bobae",
      "category": "인기",
      "author": "화끈한청바..",
      "views": 8533,
      "likes": 49,
      "comments": 15,
      "popularity_score": 8676,
      "crawled_time": "2026-04-29T09:42:24.481645"
    },
    {
      "title": "이윤희 실종사건...20년만에 나온제보,숨겨진 공백이 흔들립..",
      "url": "https://www.bobaedream.co.kr/view?code=best&No=984302&vdate=",
      "site": "bobae",
      "category": "인기",
      "author": "별반지",
      "views": 7892,
      "likes": 200,
      "comments": 18,
      "popularity_score": 8346,
      "crawled_time": "2026-04-29T09:42:24.481646"
    },
    {
      "title": "여자들이 잘생긴 남자를 좋아하는 이유",
      "url": "https://www.bobaedream.co.kr/view?code=best&No=984339&vdate=",
      "site": "bobae",
      "category": "인기",
      "author": "치이이킨",
      "views": 7675,
      "likes": 59,
      "comments": 14,
      "popularity_score": 7835,
      "crawled_time": "2026-04-29T09:42:24.481647"
    },
    {
      "title": "입주자대표가 주차봉 세워놓고 5년 넘게 주차장 2칸 전용… ..",
      "url": "https://www.bobaedream.co.kr/view?code=best&No=984305&vdate=",
      "site": "bobae",
      "category": "인기",
      "author": "코네티컷",
      "views": 6955,
      "likes": 95,
      "comments": 30,
      "popularity_score": 7235,
      "crawled_time": "2026-04-29T09:42:24.481650"
    },
    {
      "title": "학교 체벌이 사라지게 된 일등공신",
      "url": "https://www.bobaedream.co.kr/view?code=best&No=984363&vdate=",
      "site": "bobae",
      "category": "인기",
      "author": "우량주",
      "views": 5825,
      "likes": 86,
      "comments": 32,
      "popularity_score": 6093,
      "crawled_time": "2026-04-29T09:42:24.481651"
    },
    {
      "title": "탈덕수용소가 내야 할 벌금",
      "url": "https://www.bobaedream.co.kr/view?code=best&No=984314&vdate=",
      "site": "bobae",
      "category": "인기",
      "author": "콩Gspo..",
      "views": 5791,
      "likes": 93,
      "comments": 20,
      "popularity_score": 6037,
      "crawled_time": "2026-04-29T09:42:24.481651"
    },
    {
      "title": "친정서 7억 집 해줬는데 시댁에 100만씩 보내는 남편",
      "url": "https://www.bobaedream.co.kr/view?code=best&No=984357&vdate=",
      "site": "bobae",
      "category": "인기",
      "author": "진햅",
      "views": 5108,
      "likes": 38,
      "comments": 16,
      "popularity_score": 5232,
      "crawled_time": "2026-04-29T09:42:24.481652"
    },
    {
      "title": "페미 기자의 최후 ㄷㄷㄷ",
      "url": "https://www.bobaedream.co.kr/view?code=best&No=984354&vdate=",
      "site": "bobae",
      "category": "인기",
      "author": "썩열이나라",
      "views": 4721,
      "likes": 30,
      "comments": 7,
      "popularity_score": 4802,
      "crawled_time": "2026-04-29T09:42:24.481653"
    },
    {
      "title": "귀화 외국인이 미필이지만 당당한 이유",
      "url": "https://www.bobaedream.co.kr/view?code=best&No=984353&vdate=",
      "site": "bobae",
      "category": "인기",
      "author": "달리는신짱..",
      "views": 4686,
      "likes": 51,
      "comments": 10,
      "popularity_score": 4818,
      "crawled_time": "2026-04-29T09:42:24.481654"
    },
    {
      "title": "입에 걸레 문 여친",
      "url": "https://www.bobaedream.co.kr/view?code=best&No=984365&vdate=",
      "site": "bobae",
      "category": "인기",
      "author": "우량주",
      "views": 4511,
      "likes": 81,
      "comments": 24,
      "popularity_score": 4745,
      "crawled_time": "2026-04-29T09:42:24.481655"
    },
    {
      "title": "대리운전 부를때 반드시 확인해야할 것",
      "url": "https://www.bobaedream.co.kr/view?code=best&No=984364&vdate=",
      "site": "bobae",
      "category": "인기",
      "author": "우량주",
      "views": 3431,
      "likes": 44,
      "comments": 7,
      "popularity_score": 3540,
      "crawled_time": "2026-04-29T09:42:24.481656"
    },
    {
      "title": "숙명여고 시험지유출 쌍둥이 근황",
      "url": "https://bbs.ruliweb.com/best/board/300143/read/74988424?orderby=recommend&range=24h&m=humor_only&t=now",
      "site": "ruliweb",
      "category": "인기",
      "author": "루리웹",
      "views": 61297,
      "likes": 290,
      "comments": 114,
      "popularity_score": 62219,
      "crawled_time": "2026-04-29T09:42:26.562772"
    },
    {
      "title": "한국 건물주의 흔한 권력.jpg",
      "url": "https://bbs.ruliweb.com/best/board/300143/read/74992291?orderby=recommend&range=24h&m=humor_only&t=now",
      "site": "ruliweb",
      "category": "인기",
      "author": "루리웹",
      "views": 45711,
      "likes": 211,
      "comments": 65,
      "popularity_score": 46328,
      "crawled_time": "2026-04-29T09:42:26.562783"
    },
    {
      "title": "기자 패던 대한민국 1위 세금 체납자 근황",
      "url": "https://bbs.ruliweb.com/best/board/300143/read/74988569?orderby=recommend&range=24h&m=humor_only&t=now",
      "site": "ruliweb",
      "category": "인기",
      "author": "루리웹",
      "views": 42921,
      "likes": 212,
      "comments": 47,
      "popularity_score": 43486,
      "crawled_time": "2026-04-29T09:42:26.562784"
    },
    {
      "title": "토요코 키즈 근황",
      "url": "https://bbs.ruliweb.com/best/board/300143/read/74989460?orderby=recommend&range=24h&m=humor_only&t=now",
      "site": "ruliweb",
      "category": "인기",
      "author": "루리웹",
      "views": 42109,
      "likes": 295,
      "comments": 113,
      "popularity_score": 43038,
      "crawled_time": "2026-04-29T09:42:26.562785"
    },
    {
      "title": "혼밥 손님이 싫어 팁 받고 싶다는 식당사장",
      "url": "https://bbs.ruliweb.com/best/board/300143/read/74983514?orderby=recommend&range=24h&m=humor_only&t=now",
      "site": "ruliweb",
      "category": "인기",
      "author": "루리웹",
      "views": 39053,
      "likes": 199,
      "comments": 104,
      "popularity_score": 39763,
      "crawled_time": "2026-04-29T09:42:26.562786"
    },
    {
      "title": "죽은 누나 돈 30만원 찾으려고 은행에 시신 들고 온 인도 남성",
      "url": "https://bbs.ruliweb.com/best/board/300143/read/74992600?orderby=recommend&range=24h&m=humor_only&t=now",
      "site": "ruliweb",
      "category": "인기",
      "author": "루리웹",
      "views": 28436,
      "likes": 212,
      "comments": 46,
      "popularity_score": 28998,
      "crawled_time": "2026-04-29T09:42:26.562787"
    },
    {
      "title": "핫딜[스팀] 택틱스 오우거 18,600원 외 가격 다양",
      "url": "https://bbs.ruliweb.com/market/board/1020/read/103762",
      "site": "ruliweb",
      "category": "인기",
      "author": "루리웹",
      "views": 28168,
      "likes": 27,
      "comments": 54,
      "popularity_score": 28384,
      "crawled_time": "2026-04-29T09:42:26.562788"
    },
    {
      "title": "또 하나 터진 커피 프랜차이즈",
      "url": "https://bbs.ruliweb.com/best/board/300143/read/74984685?orderby=recommend&range=24h&m=humor_only&t=now",
      "site": "ruliweb",
      "category": "인기",
      "author": "루리웹",
      "views": 24973,
      "likes": 219,
      "comments": 61,
      "popularity_score": 25594,
      "crawled_time": "2026-04-29T09:42:26.562789"
    },
    {
      "title": "\"검사 일찍 받을 수 있나요?\" \"하... 저기 사람들 보이세요?\"",
      "url": "https://bbs.ruliweb.com/best/board/300143/read/74989347?orderby=recommend&range=24h&m=humor_only&t=now",
      "site": "ruliweb",
      "category": "인기",
      "author": "루리웹",
      "views": 24654,
      "likes": 226,
      "comments": 67,
      "popularity_score": 25307,
      "crawled_time": "2026-04-29T09:42:26.562790"
    },
    {
      "title": "일이 즐거운 복지직 공무원",
      "url": "https://bbs.ruliweb.com/best/board/300143/read/74989244?orderby=recommend&range=24h&m=humor_only&t=now",
      "site": "ruliweb",
      "category": "인기",
      "author": "루리웹",
      "views": 24058,
      "likes": 227,
      "comments": 33,
      "popularity_score": 24611,
      "crawled_time": "2026-04-29T09:42:26.562791"
    },
    {
      "title": "[싱갤]싱글벙글 김정은 외모를 본 일본인들 반응",
      "url": "https://gall.dcinside.com/board/view/?id=dcbest&no=425144&_dcbest=1&page=1",
      "site": "dcinside",
      "category": "인기",
      "author": "외않됌",
      "views": 14636,
      "likes": 51,
      "comments": 120,
      "popularity_score": 15098,
      "crawled_time": "2026-04-29T09:42:28.162095"
    },
    {
      "title": "[이갤]“서유리, 사채업자보다 집요해” 최병길 PD, 결국 카톡까지 공개",
      "url": "https://gall.dcinside.com/board/view/?id=dcbest&no=425149&_dcbest=1&page=1",
      "site": "dcinside",
      "category": "인기",
      "author": "ㅇㅇ",
      "views": 14217,
      "likes": 66,
      "comments": 176,
      "popularity_score": 14877,
      "crawled_time": "2026-04-29T09:42:28.162110"
    },
    {
      "title": "[군갤]찰스왕: 영국 아니었으면 느그들은 프랑스어 쓰고있었다",
      "url": "https://gall.dcinside.com/board/view/?id=dcbest&no=425150&_dcbest=1&page=1",
      "site": "dcinside",
      "category": "인기",
      "author": "A-6",
      "views": 12173,
      "likes": 94,
      "comments": 182,
      "popularity_score": 12907,
      "crawled_time": "2026-04-29T09:42:28.162112"
    },
    {
      "title": "[야갤]강가에 라면 쏟고 쓰레기 버리고간 캠핑족",
      "url": "https://gall.dcinside.com/board/view/?id=dcbest&no=425131&_dcbest=1&page=1",
      "site": "dcinside",
      "category": "인기",
      "author": "ㅇㅇ(106.101)",
      "views": 11813,
      "likes": 58,
      "comments": 165,
      "popularity_score": 12424,
      "crawled_time": "2026-04-29T09:42:28.162114"
    },
    {
      "title": "[부갤]고유가 지원금 왜 한국인만 주냐며 인권위에 진정 넣은 이주민들",
      "url": "https://gall.dcinside.com/board/view/?id=dcbest&no=425158&_dcbest=1&page=1",
      "site": "dcinside",
      "category": "인기",
      "author": "ㅇㅇ(106.101)",
      "views": 11234,
      "likes": 55,
      "comments": 243,
      "popularity_score": 12073,
      "crawled_time": "2026-04-29T09:42:28.162116"
    },
    {
      "title": "[중갤]폴리마켓 지선 예측 떴다 ㅋㅋㅋㅋㅋㅋㅋ",
      "url": "https://gall.dcinside.com/board/view/?id=dcbest&no=425177&_dcbest=1&page=1",
      "site": "dcinside",
      "category": "인기",
      "author": "털털털털털또털이야",
      "views": 9905,
      "likes": 68,
      "comments": 360,
      "popularity_score": 11121,
      "crawled_time": "2026-04-29T09:42:28.162117"
    },
    {
      "title": "[특갤]에이전트가 작곡 전문적으로 잘 하게 만드는 스킬 만듬",
      "url": "https://gall.dcinside.com/board/view/?id=dcbest&no=425187&_dcbest=1&page=1",
      "site": "dcinside",
      "category": "인기",
      "author": "라치치",
      "views": 9345,
      "likes": 90,
      "comments": 125,
      "popularity_score": 9900,
      "crawled_time": "2026-04-29T09:42:28.162118"
    },
    {
      "title": "[기갤]대군부인 보고 현타왔다는 드라마 작가 지망생",
      "url": "https://gall.dcinside.com/board/view/?id=dcbest&no=425165&_dcbest=1&page=1",
      "site": "dcinside",
      "category": "인기",
      "author": "ㅇㅇ(106.101)",
      "views": 9338,
      "likes": 12,
      "comments": 135,
      "popularity_score": 9767,
      "crawled_time": "2026-04-29T09:42:28.162120"
    },
    {
      "title": "[싱갤]싱글벙글 현실적으로 좀비가 인류를 이길 수 없는 이유",
      "url": "https://gall.dcinside.com/board/view/?id=dcbest&no=425221&_dcbest=1&page=1",
      "site": "dcinside",
      "category": "인기",
      "author": "ㅇㅇ",
      "views": 9097,
      "likes": 50,
      "comments": 164,
      "popularity_score": 9689,
      "crawled_time": "2026-04-29T09:42:28.162121"
    },
    {
      "title": "[이갤]성과급 6억 현금으로 달라는 삼성전자 노조 & 하청업체",
      "url": "https://gall.dcinside.com/board/view/?id=dcbest&no=425156&_dcbest=1&page=1",
      "site": "dcinside",
      "category": "인기",
      "author": "ㅇㅇ(106.101)",
      "views": 8846,
      "likes": 35,
      "comments": 215,
      "popularity_score": 9561,
      "crawled_time": "2026-04-29T09:42:28.162122"
    },
    {
      "title": "장기보유특별공제 개정안 발의",
      "url": "https://www.ppomppu.co.kr/zboard/view.php?id=house&no=251255",
      "author": "aoldam",
      "site": "ppomppu",
      "category": "인기",
      "views": 27173,
      "likes": 21,
      "comments": 106,
      "popularity_score": 27533,
      "crawled_time": "2026-04-29T09:42:29.459361"
    },
    {
      "title": "와 진짜 중국 전기차 가격은 대단하네요",
      "url": "https://www.ppomppu.co.kr/zboard/view.php?id=car&no=968639",
      "author": "Joysoul",
      "site": "ppomppu",
      "category": "인기",
      "views": 26991,
      "likes": 8,
      "comments": 63,
      "popularity_score": 27196,
      "crawled_time": "2026-04-29T09:42:29.459370"
    },
    {
      "title": "오늘 챔스 PSG 볼보이 논란.mp",
      "url": "https://www.ppomppu.co.kr/zboard/view.php?id=soccer&no=186992",
      "author": "키쿠론",
      "site": "ppomppu",
      "category": "인기",
      "views": 24672,
      "likes": 9,
      "comments": 448,
      "popularity_score": 26034,
      "crawled_time": "2026-04-29T09:42:29.459372"
    },
    {
      "title": "신형(페리) 그랜저 실물 공개",
      "url": "https://www.ppomppu.co.kr/zboard/view.php?id=car&no=968664",
      "author": "최저가사냥꾼",
      "site": "ppomppu",
      "category": "인기",
      "views": 24300,
      "likes": 3,
      "comments": 63,
      "popularity_score": 24495,
      "crawled_time": "2026-04-29T09:42:29.459373"
    },
    {
      "title": "노란봉투법으로 쑥대밭이 된 한국",
      "url": "https://www.ppomppu.co.kr/zboard/view.php?id=stock&no=351386",
      "author": "[* 익명 *]",
      "site": "ppomppu",
      "category": "인기",
      "views": 20408,
      "likes": 28,
      "comments": 154,
      "popularity_score": 20926,
      "crawled_time": "2026-04-29T09:42:29.459373"
    },
    {
      "title": "충격적인 최근 수입차 판매 순위 feat BYD",
      "url": "https://www.ppomppu.co.kr/zboard/view.php?id=car&no=968654",
      "author": "aoldam",
      "site": "ppomppu",
      "category": "인기",
      "views": 19788,
      "likes": 10,
      "comments": 107,
      "popularity_score": 20129,
      "crawled_time": "2026-04-29T09:42:29.459374"
    },
    {
      "title": "모델YL 출고인증",
      "url": "https://www.ppomppu.co.kr/zboard/view.php?id=car&no=968672",
      "author": "아돈",
      "site": "ppomppu",
      "category": "인기",
      "views": 18925,
      "likes": 22,
      "comments": 75,
      "popularity_score": 19194,
      "crawled_time": "2026-04-29T09:42:29.459375"
    },
    {
      "title": "2027년 글로벌 기업 영업익 예상순위",
      "url": "https://www.ppomppu.co.kr/zboard/view.php?id=stock&no=351307",
      "author": "NAVER",
      "site": "ppomppu",
      "category": "인기",
      "views": 13990,
      "likes": 25,
      "comments": 28,
      "popularity_score": 14124,
      "crawled_time": "2026-04-29T09:42:29.459376"
    },
    {
      "title": "\"쿠팡 총수는 김범석\", 5년만에 규제 칼 뺀 공정위",
      "url": "https://www.ppomppu.co.kr/zboard/view.php?id=stock&no=351325",
      "author": "토빈이",
      "site": "ppomppu",
      "category": "인기",
      "views": 12365,
      "likes": 60,
      "comments": 25,
      "popularity_score": 12560,
      "crawled_time": "2026-04-29T09:42:29.459377"
    },
    {
      "title": "여기서 맞는 말을 해 줄 필요가 없음",
      "url": "https://www.ppomppu.co.kr/zboard/view.php?id=house&no=251260",
      "author": "이따가했대",
      "site": "ppomppu",
      "category": "인기",
      "views": 11971,
      "likes": 40,
      "comments": 147,
      "popularity_score": 12492,
      "crawled_time": "2026-04-29T09:42:29.459378"
    },
    {
      "title": "날벼락 세금 2억을 낼 수 없다는 28세 청년...",
      "url": "https://www.dogdrip.net/dogdrip/699087749?sort_index=popular&page=1",
      "author": "개드립",
      "site": "dogdrip",
      "category": "인기",
      "views": 0,
      "likes": 0,
      "comments": 0,
      "popularity_score": 0,
      "crawled_time": "2026-04-29T09:42:30.935826"
    },
    {
      "title": "싱글벙글 중국인 덕분에 건강해진 제주도..jpg",
      "url": "https://www.dogdrip.net/dogdrip/699081615?sort_index=popular&page=1",
      "author": "개드립",
      "site": "dogdrip",
      "category": "인기",
      "views": 0,
      "likes": 0,
      "comments": 0,
      "popularity_score": 0,
      "crawled_time": "2026-04-29T09:42:30.935836"
    },
    {
      "title": "'상대적 박탈감' 표현 싫어하는 이유.jpg",
      "url": "https://www.dogdrip.net/dogdrip/699083197?sort_index=popular&page=1",
      "author": "개드립",
      "site": "dogdrip",
      "category": "인기",
      "views": 0,
      "likes": 0,
      "comments": 0,
      "popularity_score": 0,
      "crawled_time": "2026-04-29T09:42:30.935837"
    },
    {
      "title": "인방)요새 스트리머들이 피곤함을 느낀다는 팬덤",
      "url": "https://www.dogdrip.net/dogdrip/699078828?sort_index=popular&page=1",
      "author": "개드립",
      "site": "dogdrip",
      "category": "인기",
      "views": 0,
      "likes": 0,
      "comments": 0,
      "popularity_score": 0,
      "crawled_time": "2026-04-29T09:42:30.935838"
    },
    {
      "title": "하이닉스 친구 박탈감 호소... 영구적 계급화 우려.jpg",
      "url": "https://www.dogdrip.net/dogdrip/699078051?sort_index=popular&page=1",
      "author": "개드립",
      "site": "dogdrip",
      "category": "인기",
      "views": 0,
      "likes": 0,
      "comments": 0,
      "popularity_score": 0,
      "crawled_time": "2026-04-29T09:42:30.935839"
    },
    {
      "title": "여자의 보지는 다른게 맞다.",
      "url": "https://www.dogdrip.net/dogdrip/699075949?sort_index=popular&page=1",
      "author": "개드립",
      "site": "dogdrip",
      "category": "인기",
      "views": 0,
      "likes": 0,
      "comments": 0,
      "popularity_score": 0,
      "crawled_time": "2026-04-29T09:42:30.935840"
    },
    {
      "title": "김풍 실제체급 체감 확 오는 사진",
      "url": "https://www.dogdrip.net/dogdrip/699067996?sort_index=popular&page=1",
      "author": "개드립",
      "site": "dogdrip",
      "category": "인기",
      "views": 0,
      "likes": 0,
      "comments": 0,
      "popularity_score": 0,
      "crawled_time": "2026-04-29T09:42:30.935841"
    },
    {
      "title": "귀화 외국인이 미필이지만 당당한 이유.jpg",
      "url": "https://www.dogdrip.net/dogdrip/699067865?sort_index=popular&page=1",
      "author": "개드립",
      "site": "dogdrip",
      "category": "인기",
      "views": 0,
      "likes": 0,
      "comments": 0,
      "popularity_score": 0,
      "crawled_time": "2026-04-29T09:42:30.935842"
    },
    {
      "title": "키 작게 낳아준 부모가 원망스럽다는 모쏠남",
      "url": "https://www.dogdrip.net/dogdrip/699066783?sort_index=popular&page=1",
      "author": "개드립",
      "site": "dogdrip",
      "category": "인기",
      "views": 0,
      "likes": 0,
      "comments": 0,
      "popularity_score": 0,
      "crawled_time": "2026-04-29T09:42:30.935842"
    },
    {
      "title": "요즘 젊은 남자들의 불만 포인트.jpg",
      "url": "https://www.dogdrip.net/dogdrip/699066307?sort_index=popular&page=1",
      "author": "개드립",
      "site": "dogdrip",
      "category": "인기",
      "views": 0,
      "likes": 0,
      "comments": 0,
      "popularity_score": 0,
      "crawled_time": "2026-04-29T09:42:30.935843"
    }
  ]
}